atws/__init__.py
atws/connection.py
atws/constants.py
atws/helpers.py
atws/picklist.py
atws/query.py
atws/wrapper.py
atws/monkeypatch/__init__.py
atws/monkeypatch/asdict.py
atws/monkeypatch/attributes.py
atws/monkeypatch/crud.py
atws/monkeypatch/duckpunch.py
atws/monkeypatch/marshallable.py
atws/monkeypatch/userdefinedfields.py
atws-0.5.6.dist-info/AUTHORS.rst
atws-0.5.6.dist-info/LICENSE
atws-0.5.6.dist-info/METADATA
atws-0.5.6.dist-info/WHEEL
atws-0.5.6.dist-info/top_level.txt
atws-0.5.6.dist-info/RECORD
