Metadata-Version: 2.1
Name: atws
Version: 0.5.6
Summary: python-atws is a wrapper for the AutoTask SOAP webservices API
Home-page: https://github.com/MattParr/python-atws
Author: Matt Parr
Author-email: matt@parr.geek.nz
License: MIT license
Keywords: atws Autotask API SOAP
Platform: UNKNOWN
Classifier: Development Status :: 4 - Beta
Classifier: Intended Audience :: Developers
Classifier: License :: OSI Approved :: MIT License
Classifier: Natural Language :: English
Classifier: Programming Language :: Python :: 2
Classifier: Programming Language :: Python :: 2.7
Classifier: Programming Language :: Python :: 3
Classifier: Programming Language :: Python :: 3.3
Classifier: Programming Language :: Python :: 3.4
Classifier: Programming Language :: Python :: 3.5
Requires-Dist: requests
Requires-Dist: pytz
Requires-Dist: suds-community
Requires-Dist: future
Requires-Dist: cached-property
